cvdata/__init__.py
cvdata/analyze.py
cvdata/clean.py
cvdata/common.py
cvdata/convert.py
cvdata/duplicates.py
cvdata/exclude.py
cvdata/filter.py
cvdata/mask.py
cvdata/relabel.py
cvdata/rename.py
cvdata/resize.py
cvdata/split.py
cvdata/utils.py
cvdata/visualize.py
cvdata-0.0.7.dist-info/METADATA
cvdata-0.0.7.dist-info/WHEEL
cvdata-0.0.7.dist-info/entry_points.txt
cvdata-0.0.7.dist-info/top_level.txt
cvdata-0.0.7.dist-info/RECORD
