Metadata-Version: 2.1
Name: cvdata
Version: 0.0.7
Summary: Tools for creating and manipulating computer vision datasets
Home-page: https://github.com/monocongo/cvdata
Author: James Adams
Author-email: monocongo@gmail.com
License: UNKNOWN
Platform: UNKNOWN
Classifier: License :: OSI Approved :: MIT License
Classifier: Programming Language :: Python :: 3.6
Classifier: Programming Language :: Python :: 3.7
Classifier: Operating System :: OS Independent
Provides: cvdata
Requires-Python: >=3.6,<3.8
Requires-Dist: contextlib2
Requires-Dist: lxml
Requires-Dist: ImageHash
Requires-Dist: opencv-python
Requires-Dist: pandas
Requires-Dist: pillow
Requires-Dist: tensorflow-cpu (>=2.1)
Requires-Dist: tqdm
